hearstPatterns/__init__.py
hearstPatterns/hearstPatterns.py
hearstPatterns/test/__init__.py
hearstPatterns/test/test_hearstPatterns.py
hearstPatterns-0.1.3.dist-info/LICENSE.txt
hearstPatterns-0.1.3.dist-info/METADATA
hearstPatterns-0.1.3.dist-info/WHEEL
hearstPatterns-0.1.3.dist-info/top_level.txt
hearstPatterns-0.1.3.dist-info/RECORD
